tests/__init__.py
tests/test_helix_user.py
tests/test_helix_video.py
tests/test_twitch.py
twitch/__init__.py
twitch/api.py
twitch/baseresource.py
twitch/cache.py
twitch/resource.py
twitch/chat/__init__.py
twitch/chat/chat.py
twitch/chat/irc.py
twitch/chat/message.py
twitch/helix/__init__.py
twitch/helix/helix.py
twitch/helix/models/__init__.py
twitch/helix/models/clip.py
twitch/helix/models/follow.py
twitch/helix/models/game.py
twitch/helix/models/model.py
twitch/helix/models/stream.py
twitch/helix/models/user.py
twitch/helix/models/video.py
twitch/helix/resources/__init__.py
twitch/helix/resources/clips.py
twitch/helix/resources/follows.py
twitch/helix/resources/games.py
twitch/helix/resources/resource.py
twitch/helix/resources/streams.py
twitch/helix/resources/users.py
twitch/helix/resources/videos.py
twitch/tmi/__init__.py
twitch/tmi/tmi.py
twitch/tmi/models/__init__.py
twitch/tmi/models/chatter.py
twitch/tmi/models/model.py
twitch/tmi/resources/__init__.py
twitch/tmi/resources/chatters.py
twitch/v5/__init__.py
twitch/v5/v5.py
twitch/v5/models/__init__.py
twitch/v5/models/comment.py
twitch/v5/models/model.py
twitch/v5/resources/__init__.py
twitch/v5/resources/comments.py
pillar_twitch_python-0.0.20.dist-info/LICENSE
pillar_twitch_python-0.0.20.dist-info/METADATA
pillar_twitch_python-0.0.20.dist-info/WHEEL
pillar_twitch_python-0.0.20.dist-info/top_level.txt
pillar_twitch_python-0.0.20.dist-info/zip-safe
pillar_twitch_python-0.0.20.dist-info/RECORD
