Metadata-Version: 2.1
Name: pillar-twitch-python
Version: 0.0.20
Summary: Twitch module for Python
Home-page: https://github.com/pillargg/Twitch-Python
Author: Pillar
Author-email: opensource@pillar.gg
License: MIT
Keywords: Twitch API
Platform: UNKNOWN
Classifier: Development Status :: 2 - Pre-Alpha
Classifier: Intended Audience :: Developers
Classifier: License :: OSI Approved :: MIT License
Classifier: Natural Language :: English
Classifier: Programming Language :: Python :: 3.7
Classifier: Programming Language :: Python :: 3.8
Requires-Python: >=3.7
Requires-Dist: requests
Requires-Dist: rx (>=3.0.0)
